{"name":"Buying products that are in the shopping cart","id":"product-purchase-flow-test;buying-products-that-are-in-the-shopping-cart","testSteps":[{"number":1,"description":"Given the \u0027user\u0027 is located on the opencart website","duration":13829,"startTime":"2023-07-25T13:52:07.275990-05:00[America/Bogota]","screenshots":[{"screenshot":"e3bfce1ae1ed89259c459f0a43636f73e8b58f244ea56022b802ba59bf1eeb11.png","timeStamp":1690311141105}],"result":"SUCCESS","precondition":false,"level":0,"children":[{"number":2,"description":"user opens the http://opencart.abstracta.us/index.php?route\u003dcommon/home","duration":13514,"startTime":"2023-07-25T13:52:07.568893-05:00[America/Bogota]","screenshots":[{"screenshot":"e3bfce1ae1ed89259c459f0a43636f73e8b58f244ea56022b802ba59bf1eeb11.png","timeStamp":1690311141082}],"result":"SUCCESS","precondition":false,"level":1}]},{"number":3,"description":"When the user adds products to the cart","duration":6381,"startTime":"2023-07-25T13:52:21.115747-05:00[America/Bogota]","screenshots":[{"screenshot":"aa4aa05cef072b065e005ea35e983dcfbba332356207d694b4b55684e34796e4.png","timeStamp":1690311147497}],"result":"SUCCESS","precondition":false,"level":0,"children":[{"number":4,"description":"User add products","duration":6356,"startTime":"2023-07-25T13:52:21.134264-05:00[America/Bogota]","screenshots":[{"screenshot":"32e94f2dd9dc1f322c3ca64c096bef7841e83aaa14e320411a7e2360b1732d20.png","timeStamp":1690311142796},{"screenshot":"aa4aa05cef072b065e005ea35e983dcfbba332356207d694b4b55684e34796e4.png","timeStamp":1690311147490}],"result":"SUCCESS","precondition":false,"level":1,"children":[{"number":5,"description":"user enters \u00271\u0027 into Quantity","duration":2281,"startTime":"2023-07-25T13:52:24.096864-05:00[America/Bogota]","screenshots":[{"screenshot":"c6fb058f915f2b39b219368a969fedd1ef3f1c6c64e3b3eb0dc6d175c46ac116.png","timeStamp":1690311145087},{"screenshot":"b675255d14a7b7f660b0e210030c95ac34fc93d6bec7325525ec8aa103253f1c.png","timeStamp":1690311146377}],"result":"SUCCESS","precondition":false,"level":2}]}]},{"number":6,"description":"Then the user can view 2 products in the cart","duration":2231,"startTime":"2023-07-25T13:52:27.497918-05:00[America/Bogota]","screenshots":[{"screenshot":"9a31dc50bd6bb8b7595ad86a67d8ada6ff6b6eacbb2914a65eea54825e4b9fb4.png","timeStamp":1690311149729}],"result":"SUCCESS","precondition":false,"level":0,"children":[{"number":7,"description":"Then products are","duration":2166,"startTime":"2023-07-25T13:52:27.556749-05:00[America/Bogota]","screenshots":[{"screenshot":"7efcca6d67b80d20fc10d777d5bcf96b2f111424f57bf7da5af3993a661b7536.png","timeStamp":1690311148393},{"screenshot":"9a31dc50bd6bb8b7595ad86a67d8ada6ff6b6eacbb2914a65eea54825e4b9fb4.png","timeStamp":1690311149723}],"result":"SUCCESS","precondition":false,"level":1}]},{"number":8,"description":"When you checkout as a guest","duration":17954,"startTime":"2023-07-25T13:52:29.730132-05:00[America/Bogota]","screenshots":[{"screenshot":"0ade61e309f0b59a3868bc506718c774ded01bad1585a8e0fe752d4e4d612018.png","timeStamp":1690311167684}],"result":"SUCCESS","precondition":false,"level":0,"children":[{"number":9,"description":"User complete the checkout","duration":17938,"startTime":"2023-07-25T13:52:29.740867-05:00[America/Bogota]","screenshots":[{"screenshot":"0ade61e309f0b59a3868bc506718c774ded01bad1585a8e0fe752d4e4d612018.png","timeStamp":1690311167679}],"result":"SUCCESS","precondition":false,"level":1,"children":[{"number":10,"description":"User fill out form","duration":15868,"startTime":"2023-07-25T13:52:31.804475-05:00[America/Bogota]","screenshots":[{"screenshot":"de154872ec032b54b77b6316a84bc89466d5aedb4857d5ea7688e798d32f6355.png","timeStamp":1690311152788},{"screenshot":"0ade61e309f0b59a3868bc506718c774ded01bad1585a8e0fe752d4e4d612018.png","timeStamp":1690311167673}],"result":"SUCCESS","precondition":false,"level":2,"children":[{"number":11,"description":"user enters \u0027Prueba\u0027 into Name","duration":1304,"startTime":"2023-07-25T13:52:32.790758-05:00[America/Bogota]","screenshots":[{"screenshot":"de154872ec032b54b77b6316a84bc89466d5aedb4857d5ea7688e798d32f6355.png","timeStamp":1690311152797},{"screenshot":"f59eb881f82aa253d85c351c76db2035928942d96b1cfeeb8de20498586aa6b3.png","timeStamp":1690311154095}],"result":"SUCCESS","precondition":false,"level":3},{"number":12,"description":"user enters \u0027Apellido\u0027 into Last Name","duration":980,"startTime":"2023-07-25T13:52:34.097111-05:00[America/Bogota]","screenshots":[{"screenshot":"f59eb881f82aa253d85c351c76db2035928942d96b1cfeeb8de20498586aa6b3.png","timeStamp":1690311154104},{"screenshot":"668e15efb7fe5f18e36dc0af9bb33586714a65a10a57262050d6c1135f02891f.png","timeStamp":1690311155077}],"result":"SUCCESS","precondition":false,"level":3},{"number":13,"description":"user enters \u0027pruebacheckout1@yopmail.com\u0027 into Email","duration":1026,"startTime":"2023-07-25T13:52:35.079277-05:00[America/Bogota]","screenshots":[{"screenshot":"668e15efb7fe5f18e36dc0af9bb33586714a65a10a57262050d6c1135f02891f.png","timeStamp":1690311155087},{"screenshot":"27cb640669886e9e646dd3766edc057ab983dff5d93da500a1ca07362ad1e047.png","timeStamp":1690311156106}],"result":"SUCCESS","precondition":false,"level":3},{"number":14,"description":"user enters \u0027301001111\u0027 into Phone","duration":970,"startTime":"2023-07-25T13:52:36.108324-05:00[America/Bogota]","screenshots":[{"screenshot":"27cb640669886e9e646dd3766edc057ab983dff5d93da500a1ca07362ad1e047.png","timeStamp":1690311156115},{"screenshot":"de3362f939a1d9f0d8d16cbfa18bc80ecce3537acff5394735c32cb4d582cf17.png","timeStamp":1690311157079}],"result":"SUCCESS","precondition":false,"level":3},{"number":15,"description":"user enters \u0027calle 45\u0027 into Address 1","duration":946,"startTime":"2023-07-25T13:52:37.081031-05:00[America/Bogota]","screenshots":[{"screenshot":"de3362f939a1d9f0d8d16cbfa18bc80ecce3537acff5394735c32cb4d582cf17.png","timeStamp":1690311157087},{"screenshot":"366775e9bc93cfbdda12e67c927badc7e7706ea424b94ddcc092ef3fbbdf57a6.png","timeStamp":1690311158027}],"result":"SUCCESS","precondition":false,"level":3},{"number":16,"description":"user enters \u0027Medellin\u0027 into City","duration":947,"startTime":"2023-07-25T13:52:38.029657-05:00[America/Bogota]","screenshots":[{"screenshot":"366775e9bc93cfbdda12e67c927badc7e7706ea424b94ddcc092ef3fbbdf57a6.png","timeStamp":1690311158036},{"screenshot":"16729064856b233b1ebf1a47678a8035199e807fcea5bd5f0f2091dcbb80b786.png","timeStamp":1690311158977}],"result":"SUCCESS","precondition":false,"level":3},{"number":17,"description":"user enters \u0027050029\u0027 into Post Code","duration":927,"startTime":"2023-07-25T13:52:38.979366-05:00[America/Bogota]","screenshots":[{"screenshot":"16729064856b233b1ebf1a47678a8035199e807fcea5bd5f0f2091dcbb80b786.png","timeStamp":1690311158987},{"screenshot":"3e7df4acad93fca5aec268683ace3365c37f064b739df4bcbf8a2248b31191ba.png","timeStamp":1690311159906}],"result":"SUCCESS","precondition":false,"level":3},{"number":18,"description":"user selects 47 in Country","duration":944,"startTime":"2023-07-25T13:52:39.911844-05:00[America/Bogota]","screenshots":[{"screenshot":"3e7df4acad93fca5aec268683ace3365c37f064b739df4bcbf8a2248b31191ba.png","timeStamp":1690311159918},{"screenshot":"7719834bfb57ab893a4e4f41486c8f2f57dd3106b949bf267c241d9e29399343.png","timeStamp":1690311160856}],"result":"SUCCESS","precondition":false,"level":3},{"number":19,"description":"user selects 721 in State","duration":884,"startTime":"2023-07-25T13:52:40.858663-05:00[America/Bogota]","screenshots":[{"screenshot":"7719834bfb57ab893a4e4f41486c8f2f57dd3106b949bf267c241d9e29399343.png","timeStamp":1690311160866},{"screenshot":"4c963c4a6e5c6388e5e53fd1a420857f94a4dc10c2a59d6ddf4508c8d8d6ea3d.png","timeStamp":1690311161742}],"result":"SUCCESS","precondition":false,"level":3},{"number":20,"description":"user clicks on Button continue","duration":925,"startTime":"2023-07-25T13:52:41.749062-05:00[America/Bogota]","screenshots":[{"screenshot":"4c963c4a6e5c6388e5e53fd1a420857f94a4dc10c2a59d6ddf4508c8d8d6ea3d.png","timeStamp":1690311161755},{"screenshot":"02099802fb183be80e7ea26dfefb7df673f0a18b20bf480f7810649fdcff70ea.png","timeStamp":1690311162674}],"result":"SUCCESS","precondition":false,"level":3},{"number":21,"description":"user enters \u0027Prueba\u0027 into comment","duration":945,"startTime":"2023-07-25T13:52:42.676554-05:00[America/Bogota]","screenshots":[{"screenshot":"02099802fb183be80e7ea26dfefb7df673f0a18b20bf480f7810649fdcff70ea.png","timeStamp":1690311162682},{"screenshot":"455f665ba8e29ea3dc64f5d860bb73241153451f63addf559e7450f04a9559ee.png","timeStamp":1690311163621}],"result":"SUCCESS","precondition":false,"level":3},{"number":22,"description":"user clicks on Button shipping","duration":914,"startTime":"2023-07-25T13:52:43.623502-05:00[America/Bogota]","screenshots":[{"screenshot":"455f665ba8e29ea3dc64f5d860bb73241153451f63addf559e7450f04a9559ee.png","timeStamp":1690311163629},{"screenshot":"079f0bb753610688d29d81564efc72226c16ae6707196fcefddfc9f6184315d4.png","timeStamp":1690311164538}],"result":"SUCCESS","precondition":false,"level":3},{"number":23,"description":"user clicks on agree","duration":789,"startTime":"2023-07-25T13:52:44.541021-05:00[America/Bogota]","screenshots":[{"screenshot":"079f0bb753610688d29d81564efc72226c16ae6707196fcefddfc9f6184315d4.png","timeStamp":1690311164547},{"screenshot":"ce761d6afdde6e82db4e7e6c354bb0804aa3a45f9d68cc6ee504548b0be536f5.png","timeStamp":1690311165330}],"result":"SUCCESS","precondition":false,"level":3},{"number":24,"description":"user clicks on Button payment","duration":901,"startTime":"2023-07-25T13:52:45.332618-05:00[America/Bogota]","screenshots":[{"screenshot":"ce761d6afdde6e82db4e7e6c354bb0804aa3a45f9d68cc6ee504548b0be536f5.png","timeStamp":1690311165339},{"screenshot":"83f5d5fe80ba3f353f9cf6d117bf3591d4ffc704e88b6275094baeb697f538a7.png","timeStamp":1690311166233}],"result":"SUCCESS","precondition":false,"level":3},{"number":25,"description":"user clicks on Button confirm order","duration":1430,"startTime":"2023-07-25T13:52:46.235618-05:00[America/Bogota]","screenshots":[{"screenshot":"83f5d5fe80ba3f353f9cf6d117bf3591d4ffc704e88b6275094baeb697f538a7.png","timeStamp":1690311166243},{"screenshot":"0ade61e309f0b59a3868bc506718c774ded01bad1585a8e0fe752d4e4d612018.png","timeStamp":1690311167666}],"result":"SUCCESS","precondition":false,"level":3}]}]}]},{"number":26,"description":"Then the user must be able to view the purchase confirmation.","duration":753,"startTime":"2023-07-25T13:52:47.684659-05:00[America/Bogota]","screenshots":[{"screenshot":"e376471a09c4b3c29e20443123974a916a41dace46eb4fbea72568fea5dd76ff.png","timeStamp":1690311168437}],"result":"SUCCESS","precondition":false,"level":0,"children":[{"number":27,"description":"Then the order confirmation message","duration":740,"startTime":"2023-07-25T13:52:47.691852-05:00[America/Bogota]","screenshots":[{"screenshot":"e376471a09c4b3c29e20443123974a916a41dace46eb4fbea72568fea5dd76ff.png","timeStamp":1690311168431}],"result":"SUCCESS","precondition":false,"level":1}]}],"userStory":{"id":"product-purchase-flow-test","storyName":"Product purchase flow test","path":"add_products_to_cart.feature","narrative":"  I as a user\n  I want to select products\n  To be able to buy them","type":"feature"},"featureTag":{"name":"Product purchase flow test","type":"feature","displayName":"Product purchase flow test"},"title":"Buying products that are in the shopping cart","description":"","backgroundTitle":"Add two products to cart","backgroundDescription":"","tags":[{"name":"Product purchase flow test","type":"feature","displayName":"Product purchase flow test"}],"startTime":"2023-07-25T13:52:07.155638-05:00[America/Bogota]","duration":41284,"projectKey":"","sessionId":"14e20f47d1a40d0b0f98e23f9003079c","driver":"chrome:user","isManualTestingUpToDate":false,"manual":false,"testSource":"Cucumber","actors":[{"name":"user","can":["browse the web"]}],"result":"SUCCESS"}